README
setup.cfg
setup.py
hoonds/__init__.py
hoonds/errors.py
hoonds/logging.py
hoonds.egg-info/PKG-INFO
hoonds.egg-info/SOURCES.txt
hoonds.egg-info/dependency_links.txt
hoonds.egg-info/requires.txt
hoonds.egg-info/top_level.txt
hoonds/patterns/__init__.py
hoonds/patterns/observer.py
hoonds/patterns/singleton.py